sbpl/__init__.py
sbpl-0.1.1.dist-info/LICENSE
sbpl-0.1.1.dist-info/METADATA
sbpl-0.1.1.dist-info/WHEEL
sbpl-0.1.1.dist-info/top_level.txt
sbpl-0.1.1.dist-info/RECORD
